charmlibs/interfaces/__init__.py
charmlibs_interfaces-1.0.0a1.dist-info/METADATA
charmlibs_interfaces-1.0.0a1.dist-info/WHEEL
charmlibs_interfaces-1.0.0a1.dist-info/RECORD
