Metadata-Version: 2.4
Name: charmlibs-interfaces
Version: 1.0.0a1
Summary: The charmlibs.interfaces namespace. This package should not be installed.
Project-URL: Documentation, https://documentation.ubuntu.com/charmlibs
Project-URL: Repository, https://github.com/canonical/charmlibs
Project-URL: Issues, https://github.com/canonical/charmlibs/issues
Author: The Charm Tech team at Canonical Ltd.
Classifier: Development Status :: 5 - Production/Stable
Classifier: Intended Audience :: Developers
Classifier: License :: OSI Approved :: Apache Software License
Classifier: Operating System :: POSIX :: Linux
Classifier: Programming Language :: Python :: 3
Requires-Python: >=3.10
